PyOdbDesignLib.py
pyodbdesignlib-0.0.1.dist-info/METADATA
pyodbdesignlib-0.0.1.dist-info/WHEEL
pyodbdesignlib-0.0.1.dist-info/licenses/LICENSE
pyodbdesignlib-0.0.1.dist-info/RECORD
