Metadata-Version: 2.1
Name: PyOdbDesignLib
Version: 0.0.1
Summary: Thin Python3 wrapper for the (C++) OdbDesignLib
Project-URL: Homepage, https://nam20485.github.io/OdbDesign/
Project-URL: Repository, https://github.com/nam20485/OdbDesign
Project-URL: Bug Tracker, https://github.com/nam20485/OdbDesign/issues
Author-email: Nathan Miller <nmiller217+odbdesign@gmail.com>
Maintainer-email: Nathan Miller <nmiller217@gmail.com>
License: MIT License
License-File: LICENSE
Keywords: Odb,Odb++
Classifier: License :: OSI Approved :: MIT License
Classifier: Operating System :: POSIX :: Linux
Classifier: Programming Language :: Python :: 3
Requires-Python: >=3.7
